__init__.py
scheduler/__init__.py
scheduler/functionmap.py
scheduler/timekeeper.py
tests/__init__.py
tests/test_function_map.py
tests/test_module.py
worker/__init__.py
worker/worker_aps.py
seledri_dennsgh-0.0.1.dist-info/LICENSE
seledri_dennsgh-0.0.1.dist-info/METADATA
seledri_dennsgh-0.0.1.dist-info/WHEEL
seledri_dennsgh-0.0.1.dist-info/top_level.txt
seledri_dennsgh-0.0.1.dist-info/RECORD
