Metadata-Version: 2.1
Name: seledri_dennsgh
Version: 0.0.1
Summary: Timekeeping and scheduling
Author-email: dennis <denngohis@gmail.com>
Project-URL: Homepage, https://github.com/dennsgh/seledri
Project-URL: Issues, https://github.com/dennsgh/seledri/issues
Classifier: Programming Language :: Python :: 3
Classifier: License :: OSI Approved :: Apache Software License
Classifier: Operating System :: OS Independent
Requires-Python: >=3.8
License-File: LICENSE
